calculyfy/CalculyFy.py
calculyfy/__init__.py
calculyfy/cli.py
CalculyFy-1.0.dist-info/METADATA
CalculyFy-1.0.dist-info/WHEEL
CalculyFy-1.0.dist-info/entry_points.txt
CalculyFy-1.0.dist-info/top_level.txt
CalculyFy-1.0.dist-info/RECORD
