Metadata-Version: 2.1
Name: CalculyFy
Version: 1.0
Requires: colorama
